SessionSmith/__init__.py
SessionSmith/compare.py
SessionSmith/core.py
SessionSmith/formats.py
SessionSmith/info.py
SessionSmith/jupyter_utils.py
SessionSmith/manager.py
SessionSmith/serializers.py
SessionSmith/tracer.py
SessionSmith/utils.py
SessionSmith/version_control.py
SessionSmith/visualizer.py
SessionSmith/visualizer_arrays.py
SessionSmith/visualizer_generic.py
sessionsmith-0.1.4.dist-info/licenses/LICENSE
sessionsmith-0.1.4.dist-info/METADATA
sessionsmith-0.1.4.dist-info/WHEEL
sessionsmith-0.1.4.dist-info/top_level.txt
sessionsmith-0.1.4.dist-info/RECORD
